{"properties": {"relative_url": {"type": "string"}, "excerpt": {"type": "string"}, "addr_desc": {"type": "string"}, "street": {"type": "string"}, "id": {"type": "long"}, "city": {"type": "string"}, "author": {"properties": {"first_name": {"type": "string"}, "last_name": {"type": "string"}, "description": {"type": "string"}, "url": {"type": "string"}, "slug": {"type": "string"}, "nickname": {"type": "string"}, "id": {"type": "long"}, "name": {"type": "string"}}}, "state": {"type": "string"}, "content": {"type": "string"}, "comment_count": {"type": "long"}, "type": {"type": "string"}, "email": {"properties": {"addr": {"type": "string"}, "desc": {"type": "string"}}}, "zip_code": {"type": "string"}, "status": {"type": "string"}, "fax": {"properties": {"num": {"type": "string"}, "desc": {"type": "string"}}}, "parent": {"type": "long"}, "web": {"properties": {"url": {"type": "string"}, "label": {"type": "string"}}}, "phone": {"properties": {"num": {"type": "string"}, "desc": {"type": "string"}}}, "date": {"type": "date", "format": "dateOptionalTime"}, "sitewide_desc": {"type": "string"}, "slug": {"type": "string"}, "comment_status": {"type": "string"}, "title_plain": {"type": "string"}, "url": {"type": "string"}, "title": {"type": "string"}, "modified": {"type": "date", "format": "dateOptionalTime"}, "thumbnail": {"properties": {"images": {"properties": {"full": {"properties": {"url": {"type": "string"}, "width": {"type": "long"}, "height": {"type": "long"}}}, "post_thumbnail": {"properties": {"url": {"type": "string"}, "width": {"type": "long"}, "height": {"type": "long"}}}, "post_image_2x": {"properties": {"url": {"type": "string"}, "width": {"type": "long"}, "height": {"type": "long"}}}, "post_thumbnail_2x": {"properties": {"url": {"type": "string"}, "width": {"type": "long"}, "height": {"type": "long"}}}, "large": {"properties": {"url": {"type": "string"}, "width": {"type": "long"}, "height": {"type": "long"}}}, "post_image": {"properties": {"url": {"type": "string"}, "width": {"type": "long"}, "height": {"type": "long"}}}}}, "alt_text": {"type": "string"}, "description": {"type": "string"}, "size": {"type": "string"}}}, "attn": {"type": "string"}, "order": {"type": "long"}}}