{
    "properties": {
        "relative_url": {
            "type": "string"
        },
        "excerpt": {
            "type": "string"
        },
        "has_parent": {
            "type": "boolean"
        },
        "section_date_to": {
            "type": "string"
        },
        "id": {
            "index": "not_analyzed",
            "type": "long"
        },
        "author": {
            "properties": {
                "first_name": {
                    "type": "string"
                },
                "last_name": {
                    "type": "string"
                },
                "description": {
                    "type": "string"
                },
                "url": {
                    "type": "string"
                },
                "id": {
                    "type": "long"
                },
                "nickname": {
                    "type": "string"
                },
                "slug": {
                    "type": "string"
                },
                "name": {
                    "type": "string"
                }
            }
        },
        "content": {
            "type": "string"
        },
        "comment_count": {
            "type": "long"
        },
        "type": {
            "type": "string"
        },
        "thumbnail": {
            "properties": {
                "images": {
                    "properties": {
                        "full": {
                            "properties": {
                                "url": {
                                    "type": "string"
                                },
                                "width": {
                                    "type": "long"
                                },
                                "height": {
                                    "type": "long"
                                }
                            }
                        },
                        "post_thumbnail": {
                            "properties": {
                                "url": {
                                    "type": "string"
                                },
                                "width": {
                                    "type": "long"
                                },
                                "height": {
                                    "type": "long"
                                }
                            }
                        },
                        "post_image_2x": {
                            "properties": {
                                "url": {
                                    "type": "string"
                                },
                                "width": {
                                    "type": "long"
                                },
                                "height": {
                                    "type": "long"
                                }
                            }
                        },
                        "post_thumbnail_2x": {
                            "properties": {
                                "url": {
                                    "type": "string"
                                },
                                "width": {
                                    "type": "long"
                                },
                                "height": {
                                    "type": "long"
                                }
                            }
                        },
                        "large": {
                            "properties": {
                                "url": {
                                    "type": "string"
                                },
                                "width": {
                                    "type": "long"
                                },
                                "height": {
                                    "type": "long"
                                }
                            }
                        },
                        "post_image": {
                            "properties": {
                                "url": {
                                    "type": "string"
                                },
                                "width": {
                                    "type": "long"
                                },
                                "height": {
                                    "type": "long"
                                }
                            }
                        }
                    }
                },
                "alt_text": {
                    "type": "string"
                },
                "description": {
                    "type": "string"
                },
                "size": {
                    "type": "string"
                }
            }
        },
        "status": {
            "type": "string"
        },
        "parent": {
            "index": "not_analyzed",
            "type": "long"
        },
        "section_date_from": {
            "type": "string"
        },
        "date": {
            "type": "date",
            "format": "dateOptionalTime"
        },
        "slug": {
            "type": "string"
        },
        "comment_status": {
            "type": "string"
        },
        "title_plain": {
            "type": "string"
        },
        "url": {
            "type": "string"
        },
        "title": {
            "type": "string"
        },
        "modified": {
            "type": "date",
            "format": "dateOptionalTime"
        },
        "order": {
            "type": "long"
        },
        "item_date": {
            "type": "string"
        }
    }
}